Metadata-Version: 2.1
Name: pyawair
Version: 0.0.12
Summary: Python binding for Awair Air Quality Device API
Home-page: https://github.com/netmanchris/pyawair
Author: netmanchris
Author-email: chris_young@me.com
License: Apache2
Keywords: getawair Awair
Platform: UNKNOWN
Classifier: Development Status :: 3 - Alpha
Classifier: Intended Audience :: Developers
Classifier: Intended Audience :: System Administrators
Classifier: License :: OSI Approved :: Apache Software License
Classifier: Programming Language :: Python
Classifier: Natural Language :: English
Classifier: Operating System :: OS Independent
Classifier: Topic :: Software Development :: Libraries :: Python Modules
Provides-Extra: test
Provides-Extra: dev
